[
    {
        "title": "Israele riaprirà il varco di Erez",
        "date_raw": "April 05, 2024",
        "date": "2024-04-05",
        "url": "https://www.ilpost.it/mondo/",
        "news_url": "https://www.ilpost.it/2024/04/05/israele-apre-varco-erez/",
        "subtitle": "E consentirà l'utilizzo del porto di Ashdod per far arrivare aiuti umanitari nel nord di Gaza: il governo israeliano lo ha deciso dopo le forti pressioni degli Stati Uniti degli ultimi giorni ",
        "content": "La portavoce del Consiglio per la sicurezza nazionale degli Stati Uniti Adrienne Watson  che Israele ha accettato di aprire il varco di Erez, che collega il territorio israeliano alla Striscia di Gaza, e di utilizzare il porto di Ashdod per consentire l’arrivo di aiuti umanitari nel nord di Gaza e aumentare le consegne direttamente dalla Giordania. Watson ha anche detto che queste decisioni sono state prese dal governo del primo ministro israeliano Benjamin Netanyahu su richiesta del presidente statunitense Joe Biden.Dopo che lunedì l’esercito israeliano  sette operatori della ong World Central Kitchen (WCK) nella Striscia di Gaza, Biden aveva fatto le dichiarazioni più dure contro Israele da quando è cominciata la guerra: aveva detto di essere «arrabbiato e distrutto», e aveva accusato Israele di non fare abbastanza per proteggere i civili della Striscia e gli operatori delle ong. Lo scontento nei confronti delle azioni del governo israeliano è stato ribadito giovedì pomeriggio durante una telefonata con Netanyahu, durante la quale Biden ha detto che il sostegno degli Stati Uniti nella guerra dipende da come Israele provvederà a proteggere i civili a Gaza e gli operatori umanitari. Dopodiché è arrivata la decisione del governo israeliano su Erez e Ashdod.Il varco di Erez, prima dell’invasione israeliana, era uno dei principali punto di frontiera di terra fra la Striscia e il territorio israeliano. Il varco permetteva tra l’altro a migliaia di pendolari palestinesi di andare al lavoro ed era stato chiuso dopo l’attacco di Hamas dello scorso 7 ottobre. Il porto di Ashdod è uno dei due più grandi porti mercantili di Israele: si trova ad Ashdod, circa 40 chilometri a sud di Tel Aviv e circa 25 chilometri a nord di Gaza.Le Nazioni Unite hanno commentato positivamente, ma con cautela, la notizia della riapertura del varco di Erez e del porto di Ashdod dicendo, attraverso il portavoce del segretario generale Stéphane Dujarric, che si dovrà vedere come tale decisione verrà implementata: «Abbiamo bisogno di un cessate il fuoco umanitario e di un massiccio afflusso di aiuti», ha detto. Quasi tutti gli aiuti ammessi a Gaza dall’inizio della conflitto sono entrati attraverso due punti di passaggio principali: Kerem Shalom e Rafah, entrambi nel sud, al confine tra l’Egitto e Israele. Ma trasportare convogli di camion dai varchi di frontiera meridionali verso nord è difficile e pericoloso: le strade sono state danneggiate dai bombardamenti israeliani e il percorso è ostacolato dai checkpoint. Gli aiuti a cui è stato consentito finora di attraversare i varchi del confine meridionale di Gaza sono stati insufficienti rispetto alla necessità di sopravvivenza. Nel frattempo Save The Children ha fatto sapere che nel nord della Striscia di Gaza un bambino su tre, sotto i due anni, soffre di grave malnutrizione, stime che sono raddoppiate rispetto a gennaio.",
        "ranked": 0,
        "placed": "Abroad",
        "epoch": 1712300407.0315337,
        "language": "IT",
        "source": "ilPost",
        "local_time": "2024-04-05 09:00:07"
    },
    {
        "title": "La Spagna ha detto che riconoscerà lo Stato di Palestina",
        "date_raw": "April 04, 2024",
        "date": "2024-04-04",
        "url": "https://www.ilpost.it/mondo/",
        "news_url": "https://www.ilpost.it/2024/04/04/spagna-riconoscimento-palestina/",
        "subtitle": "",
        "content": "Mercoledì il ministro degli Esteri della Spagna José Manuel Albares  che entro luglio il governo spagnolo riconoscerà lo Stato di Palestina. In un incontro con alcuni giornalisti a Bruxelles, Albares ha detto che «abbiamo bisogno di un vero Stato palestinese» e che «le persone palestinesi non devono essere condannate a essere per sempre rifugiate». Il primo ministro spagnolo, il socialista Pedro Sánchez,  che il paese avrebbe riconosciuto la Palestina come Stato «entro questa legislatura», per poi accorciare i tempi alla prossima estate.Riconoscere uno Stato significa avviare relazioni diplomatiche ufficiali che in genere prevedono lo scambio di ambasciatori o altro personale diplomatico; nel caso della Palestina, però, il riconoscimento internazionale ha un alto valore simbolico e politico. La Spagna aveva approvato  per il riconoscimento dello Stato di Palestina nel 2014, dieci anni fa: tuttavia in seguito sia i governi di centrodestra di Mariano Rajoy sia quelli di Sánchez avevano sostenuto che il riconoscimento ufficiale della Palestina avrebbe dovuto essere formalizzato solo insieme a tutti gli altri paesi dell’Unione Europea.L’attuale governo di Sánchez, in particolare, è stato uno dei principali critici delle operazioni militari avviate da Israele nella Striscia di Gaza dopo i violenti attacchi compiuti lo scorso 7 ottobre in territorio israeliano dal gruppo palestinese di Hamas. Secondo Albares adesso «il riconoscimento dello Stato di Palestina è la migliore garanzia di sicurezza per Israele».Al momento la Palestina è riconosciuta da quasi due terzi degli stati membri delle Nazioni Unite, ovvero da gran parte degli stati dell’America Latina, dell’Africa, dell’Asia e dell’Europa orientale. In passato anche il Parlamento Europeo aveva approvato una risoluzione in cui diceva di sostenere in linea di principio un stato palestinese entro , ma al momento solo nove dei 27 paesi membri dell’Unione lo riconoscono: Bulgaria, Cipro, Malta, Polonia, Repubblica Ceca, Romania, Slovacchia, Svezia e Ungheria. Di questi, la  è stato il primo e unico paese a riconoscere la Palestina quando era già un paese membro dell’Unione, nel 2014, mentre gli altri lo avevano riconosciuto prima di entrare nell’Unione.A marzo i capi di governo di Spagna, Irlanda, Malta e Slovenia hanno annunciato  di essere pronti a riconoscere lo Stato di Palestina «a tempo debito», «per la pace e la sicurezza» nella regione. In Italia, dopo  nel 2015, a fine gennaio scorso l’associazione Schierarsi ha avviato  per una proposta di legge di iniziativa popolare sul tema.",
        "ranked": 12,
        "placed": "Abroad",
        "epoch": 1712300407.074977,
        "language": "IT",
        "source": "ilPost",
        "local_time": "2024-04-05 09:00:07"
    },
    {
        "title": "Jordan Bardella, il futuro dell’estrema destra francese",
        "date_raw": "April 04, 2024",
        "date": "2024-04-04",
        "url": "https://www.ilpost.it/mondo/",
        "news_url": "https://www.ilpost.it/2024/04/04/jordan-bardella-destra-francese/",
        "subtitle": "È il primo presidente del Rassemblement National a non avere il cognome Le Pen, fa comizi che somigliano più a feste che a incontri politici, ed è sostenuto dalle classi popolari e dai ceti medi",
        "content": "Jordan Bardella è il presidente del partito di estrema destra francese Rassemblement National: è il primo a non avere il cognome Le Pen, cioè quello di Jean-Marie, il fondatore del Front National (che poi ha cambiato nome in Rassemblement National), e della figlia Marine, che ha guidato il partito per diversi anni dopo che se n’era andato il padre. Bardella sarà il capolista del suo partito alle elezioni europee del prossimo giugno e alcuni giornali internazionali lo  da tempo una «stella politica» in rapida ascesa: secondo i sondaggi potrebbe portare l’estrema destra francese alla più grande vittoria mai ottenuta finora a livello nazionale.Bardella è nato nel 1995 da una famiglia di origine italiana alla periferia di Parigi. Iniziò a seguire il Front National quando aveva 16 anni, affiggendo i manifesti elettorali per la campagna presidenziale del 2012 di Marine Le Pen contro François Hollande. A partire da quel momento la sua carriera è stata rapidissima. A 19 anni, mentre studiava geografia all’Università Sorbona senza poi laurearsi, era già consigliere regionale dell’Île-de-France. Nel 2017 fu promosso a portavoce del partito e direttore nazionale di Génération Nation, la sezione giovanile del Front National, nel 2019 fu eletto al parlamento europeo e poi, nel 2022,  di Rassemblement National (RN).Da quando è alla guida del partito, Bardella ha ridato slancio a un processo di “normalizzazione” che era già stato avviato da tempo da Marine Le Pen, volto a dare un’immagine più moderata e rassicurante al Rassemblement National per lasciarsi alle spalle, almeno apparentemente, una pesante eredità razzista e antisemita e per espandere la sua base elettorale: quest’operazione è stata chiamata «dédiabolisation», “dediavolizzazione”.Il quotidiano francese   che Bardella sia «l’uomo chiave della normalizzazione» del Rassemblement National, mentre  l’ha definito «il testimonial perfetto per il rebranding del partito».Bardella è molto popolare, è presente quotidianamente su TikTok e attraverso quella che il suo staff ha definito «la strategia dei selfie» sta rendendo più accattivante la destra identitaria francese. Usa parole semplici, ma di impatto, la sua dizione è chiara e appare sempre molto calmo, mai offensivo, cortese senza essere ironico. Cura molto il suo aspetto indossando spesso abiti di un marchio olandese popolare tra i giovani di destra e che è anche piuttosto economico, ed è percepito come un politico “vicino alle persone”, anche a quelle meno abbienti: ha origini modeste, «non è laureato, si chiama Jordan e va in campagna»,  un deputato di RN a Nel frattempo si è guadagnato la simpatia anche di Vincent Bolloré, uno degli uomini più ricchi di Francia da sempre vicino alla destra cattolica e conservatrice.Jordan Bardella fa un selfie con i suoi sostenitori, Marsiglia, 3 marzo 2024 (AP Photo/Daniel Cole)Molti dei comizi di Bardella sembrano delle feste più che degli incontri politici e sono aperti da gruppi di rapper marsigliesi. Altri suoi eventi sono stati organizzati in alcune famose discoteche parigine dove si sono visti centinaia di giovani al limite dell’isteria e ragazze sul punto di piangere come se si trovassero di fronte a una rockstar. Per l’opinione pubblica, Bardella resta inoltre un personaggio in qualche modo ambiguo nei posizionamenti: «I politici sono superfici di proiezione per gli elettori. E meno la gente sa di te, più può proiettarsi»  il sondaggista Jérôme Sainte-Marie: «Penso di sapere cosa pensa Marine Le Pen. Non sono sicuro di sapere cosa pensa veramente Jordan Bardella».Bardella, hanno detto alcuni deputati e senatori a lui vicini, «è diventato un marchio», «la sua personalità, ciò che incarna, fa appello agli stessi riflessi di un consumatore». E tutto questo sembra che stia funzionando.Secondo un  realizzato dall’istituto Ipsos in collaborazione con Sciences Po, l’Institut Montaigne e la Fondation Jean-Jaurès, la lista di RN guidata da Bardella è al 31 per cento, con un vantaggio di 13 punti su Renaissance del presidente Emmanuel Macron (il Partito Socialista è all’11,5 per cento, i Verdi all’8,5 e la destra dei Repubblicani al 7, alla pari con la sinistra di La France Insoumise).Allo stesso tempo, negli ultimi mesi RN ha sia rafforzato che ampliato la propria base elettorale ed «è questa simultaneità che, per il momento, gli dà forza»,  . RN è  soprattutto dai giovani uomini, ma la percentuale delle giovani donne che lo voterebbero non è indifferente. Ed è diventato, al posto della sinistra, il partito delle classi popolari e in parte dei ceti medi: il 58 per cento degli operai e il 44 per cento degli impiegati dicono infatti di voler votare Bardella alle prossime europee, mentre alle presidenziali del 2022 la percentuale era del 36 per cento per entrambe le categorie. Il partito ha aumentato la propria popolarità anche tra i dirigenti: il 19 per cento (contro il 12 per cento del 2022) è intenzionato a sostenerlo.Ciò che  i probabili futuri elettori di Bardella sembrano essere tre questioni principali. L’insoddisfazione, innanzitutto: il 58 per cento di chi ha detto che lo voterà ha anche sostenuto di non essere per nulla soddisfatto della vita che fa. Il 65 per cento degli elettori della lista Bardella alle europee ha detto poi di considerare le proposte dei vari partiti soprattutto sui temi nazionali e solo il 35 per cento sui temi europei: in nessun altro elettorato la dimensione nazionale è così presente. Il 72 per cento ha infine detto che voterà Bardella soprattutto per dimostrare la propria opposizione al presidente della Repubblica, cioè Macron, e all’attuale governo.Secondo un  commissionato nel dicembre del 2023 dai Repubblicani (di destra) che è circolato internamente al partito ma che alcuni giornali sono riusciti ad ottenere, in caso di elezioni legislative anticipate RN vincerebbe arrivando a soli 11 seggi dalla maggioranza assoluta all’Assemblea Nazionale, cioè la camera bassa del parlamento francese. Secondo un altro sondaggio pubblicato a marzo, Bardella è anche il secondo politico più popolare in Francia, dietro solo all’ex primo ministro Edouard Philippe e davanti a Marine Le Pen.I successi di RN e di Bardella, favoriti anche da un’ascesa dell’estrema destra in tutt’Europa e non solo, sta condizionando la politica francese e la maggioranza al governo. Da tempo si parla di uno  di Macron, diventato molto evidente già con l’approvazione a fine dicembre della contestata riforma dell’immigrazione votata da tutti i partiti di destra e di estrema destra.  anche che è tale «l’entità della minaccia percepita» che deriva dal successo di Bardella che Macron avrebbe scelto il 34enne Gabriel Attal  proprio come risposta diretta all’ascesa del giovane leader dell’estrema destra. Non solo: la campagna elettorale per le europee portata avanti finora da Macron è direttamente  su una critica a Bardella: sulle tendenze antieuropeiste del suo partito, sui legami di quell’area politica con il presidente russo Vladimir Putin e la Russia, e sulle sue alleanze in Europa con formazioni come il partito di estrema destra tedesco AfD (Alternativa per la Germania), messo di recente sotto sorveglianza dai servizi segreti tedeschi. Mathieu Gallard, dell’istituto ricerca e sondaggi Ipsos, ha detto che le posizioni di RN sulla Russia non sono però la prima questione con cui la maggior parte degli elettori francesi identifica il partito: è per questo che la strategia elettorale di Macron,  anche dai suoi sostenitori e alleati, non si starebbe rivelando vincente.Marine Le Pen e Jordan Bardella all’apertura della campagna elettorale per le europee a Marsiglia, 3 marzo 2024 (AP Photo/Daniel Cole)La popolarità di Bardella ha fatto anche in modo che la sua tendenza ad allontanarsi da alcune linee del partito non abbia lasciato alcuno spazio alle critiche interne alla sua leadership. Quando Bardella si è ad esempio espresso contro i prezzi minimi per i prodotti agricoli dopo la protesta degli agricoltori ampiamente sostenuta da RN, Le Pen è dovuta  per chiarire la posizione ufficiale del partito. Tuttavia, la stessa Le Pen (che pensa già alle presidenziali del 2027) non ha mai rivolto una critica diretta a Bardella e si è sempre dimostrata pronta a difenderlo: «Domani potrei essere investita da un camion», ha detto la leader durante un’intervista televisiva, aggiungendo che in quel caso Bardella avrebbe il peso politico e il credito necessari per prendere il suo posto.",
        "ranked": 11,
        "placed": "Abroad",
        "epoch": 1712300407.1251695,
        "language": "IT",
        "source": "ilPost",
        "local_time": "2024-04-05 09:00:07"
    },
    {
        "title": "Benny Gantz, leader del partito Blu e Bianco e membro del “gabinetto di guerra” israeliano, ha chiesto elezioni anticipate",
        "date_raw": "April 04, 2024",
        "date": "2024-04-04",
        "url": "https://www.ilpost.it/mondo/",
        "news_url": "https://www.ilpost.it/2024/04/04/israele-benny-gantz-elezioni-anticipate/",
        "subtitle": "",
        "content": "Mercoledì nel corso di un intervento in televisione il politico israeliano Benny Gantz  che nel paese siano indette elezioni anticipate, il prossimo settembre. A suo dire, le elezioni anticipate sarebbero necessarie per «mantenere l’unità» del governo e «rinnovarne la fiducia» tra la popolazione. Le sua richiesta è molto rilevante perché Gantz è uno dei principali leader di opposizione (del partito centrista Blu e Bianco), che però dopo l’attacco di Hamas di ottobre è entrato a far parte di un governo di unità nazionale ed è stato nominato membro del “gabinetto di guerra” israeliano.È la prima volta da quando si è formato il governo di unità nazionale che Gantz ha chiesto elezioni anticipate, e lo ha fatto pochi giorni dopo che nel paese c’erano state  dall’inizio della guerra contro il primo ministro Benjamin Netanyahu, molto criticato dagli oppositori per la sua gestione del conflitto e dei negoziati per la liberazione degli ostaggi rapiti da Hamas. Netanyahu, leader del partito di destra Likud, ha più volte detto che non intende dimettersi e far svolgere nuove elezioni, anche perché sa che la sua popolarità è attualmente molto bassa ed è quasi certo che non vincerebbe. Gantz, al contrario, è dato in vantaggio su tutti gli altri leader politici dai sondaggi.Alle parole di Gantz ha risposto in un comunicato stampa il Likud, secondo cui Gantz dovrebbe smettere di dedicarsi a «politiche meschine mentre il suo partito si sta sgretolando». Il Likud ha anche detto che le elezioni anticipate porterebbero solo a «paralisi, divisioni, danni» e sarebbero un «colpo fatale» alle possibilità di raggiungere un accordo con Hamas sulla liberazione degli ostaggi.",
        "ranked": 17,
        "placed": "Abroad",
        "epoch": 1712300407.1409786,
        "language": "IT",
        "source": "ilPost",
        "local_time": "2024-04-05 09:00:07"
    },
    {
        "title": "A Taiwan si cercano ancora decine di dispersi",
        "date_raw": "April 04, 2024",
        "date": "2024-04-04",
        "url": "https://www.ilpost.it/mondo/",
        "news_url": "https://www.ilpost.it/2024/04/04/taiwan-terremoto-decine-dispersi/",
        "subtitle": "Il terremoto più forte degli ultimi 25 anni ha ucciso almeno dieci persone e ne ha ferite oltre mille: alcune decine sono state soccorse da alcune cave, mentre altre sono ancora isolate a causa delle frane",
        "content": "Nella parte orientale di Taiwan, nell’oceano Pacifico, stanno andando avanti le operazioni di soccorso in seguito , che mercoledì ha ucciso almeno dieci persone e ne ha ferite oltre mille. Il terremoto ha fatto crollare o collassare parzialmente una cinquantina di edifici di Hualien, la città più grande vicina all’epicentro, e costretto centinaia di persone a lasciare le proprie case: al momento si continuano a cercare  e a raggiungere centinaia di persone che sono rimaste bloccate in una zona montuosa poco fuori dalla città.Il terremoto è avvenuto alle 7:58 locali (l’1:58 in Italia) e il suo epicentro è stato rilevato al largo della costa dell’isola, circa 18 chilometri a sud di Hualien. Secondo lo US Geological Survey (l’Istituto Geologico degli Stati Uniti), ha avuto una magnitudo 7.4, mentre secondo l’Agenzia meteorologica di Taiwan di 7.2 e per quella giapponese di 7.7. A ogni modo, è avvenuto in un momento in cui migliaia di persone stavano andando al lavoro o a scuola.Il terremoto ha provocato frane e smottamenti, e ci sono state oltre 50 scosse successive di minore intensità. Il capo dell’Agenzia meteorologica di Taiwan, Wu Chien-fu,  durante una conferenza stampa che nei prossimi quattro giorni potrebbero essercene di magnitudo fino a 7.Centinaia di persone hanno passato la notte tra mercoledì e giovedì in tende o alloggi temporanei. Il sindaco di Hualien, Hsu Chen-Wei, ha detto che tutti gli edifici danneggiati in maniera grave sono stati evacuati e che le squadre di emergenza hanno cominciato a demolire quelli ritenuti irrecuperabili.Nel frattempo le autorità locali hanno detto che sono state soccorse circa sessanta persone che erano rimaste intrappolate in una cava, a causa dei danni alle strade, mentre sei che lavoravano in un’altra cava sono state portate via con mezzi aerei. Al momento circa 650 persone rimangono isolate nell’area del parco nazionale di Taroko, a nord di Hualien. Sono molte di più rispetto al centinaio di persone disperse che era stato stimato inizialmente: dipende dal fatto che buona parte di queste abbia cominciato ad avere nuovamente campo telefonico solo un giorno e mezzo dopo il terremoto. Circa trenta dipendenti di un hotel  nello stesso parco: sempre secondo le autorità taiwanesi, però, sono stati individuati grazie alle immagini riprese da alcuni droni e sembra che stiano bene.Un palazzo parzialmente collassato a causa del terremoto a Hualien, Taiwan, 4 aprile (Annabelle Chih/ Getty Images)Hualien si trova in una zona prevalentemente montuosa, motivo per cui il terremoto ha causato diverse frane che hanno bloccato le strade e i tracciati ferroviari. Nella zona ci sono inoltre molti sentieri frequentati dagli escursionisti, e un’autostrada che attraversa le montagne con molte gallerie e tratti su scogliere a picco sul mare.Il terremoto di mercoledì è stato il più grave per Taiwan da quello del 1999 nella contea di Nantou, nella parte centro-occidentale dell’isola, che uccise più di 2.400 persone e ne ferì più di 11mila. Al momento le autorità del paese stanno cercando di capire come mai non sia partita un’allerta terremoto in tutto il territorio.  ",
        "ranked": 16,
        "placed": "Abroad",
        "epoch": 1712300407.148604,
        "language": "IT",
        "source": "ilPost",
        "local_time": "2024-04-05 09:00:07"
    },
    {
        "title": "Negli ultimi tre giorni sono morte sette persone per i violenti nubifragi nell’est della Cina",
        "date_raw": "April 03, 2024",
        "date": "2024-04-03",
        "url": "https://www.ilpost.it/mondo/",
        "news_url": "https://www.ilpost.it/2024/04/03/sette-morti-grandinate-cina/",
        "subtitle": "",
        "content": "Da domenica la provincia di Jiangxi, nella Cina sud-orientale, è colpita dal nubifragio più violento dell’ultimo decennio:  racconta che ci sono stati «fulmini, pioggia battente e chicchi di grandine delle dimensioni di palline da golf». A Nanchang, il capoluogo della provincia, sono morte almeno sette persone. Secondo i giornali locali tre sono precipitate dai propri appartamenti nel sonno dopo che le fortissime raffiche di vento hanno scardinato le finestre del grattacielo in cui si trovavano. Una donna che abitava al ventesimo piano dello stesso edificio ha detto al sito di notizie  che la sua famiglia ha dovuto aggrapparsi per evitare di essere trascinata via dal vento.Almeno 550 persone sono state spostate temporaneamente in rifugi d’emergenza. In tutto finora sono state danneggiate 2.751 case e 5700 ettari di terreno. È molto raro che venti di tale intensità colpiscano una zona come Jiangxi, che è piuttosto lontana dalla costa: normalmente i tifoni, come vengono chiamati gli uragani tipici dell’Asia orientale, non si addentrano tanto in profondità sulla terraferma.",
        "ranked": 18,
        "placed": "Abroad",
        "epoch": 1712300407.1568806,
        "language": "IT",
        "source": "ilPost",
        "local_time": "2024-04-05 09:00:07"
    },
    {
        "title": "La Thailandia ha un problema di macachi molesti",
        "date_raw": "April 04, 2024",
        "date": "2024-04-04",
        "url": "https://www.ilpost.it/mondo/",
        "news_url": "https://www.ilpost.it/2024/04/04/macachi-thailandia-lopburi/",
        "subtitle": "In particolare in città turistiche come Lopburi, dove vivono a stretto contatto con la popolazione: ora le autorità vogliono trasferirli quasi tutti in grosse aree recintate",
        "content": "La città di Lopburi, circa 150 chilometri a nord di Bangkok, in Thailandia, è una meta turistica piuttosto nota per i suoi reperti archeologici, come il tempio induista di Prang Sam Yot, ma anche per le migliaia di macachi che vivono in città. Queste scimmie sono un simbolo della cultura locale e sono diventate a loro volta un’attrazione: però, a causa dei continui fastidi che arrecano ai residenti e ai visitatori, dopo alcuni tentativi fallimentari l’ente nazionale che si occupa della fauna selvatica  per cercare di gestirle.A Lopburi vivono più di 2.500 esemplari di , detto anche macaco cinomolgo o cancrivoro, un primate diffuso soprattutto nel Sud-est asiatico, in paesi come Bangladesh, Filippine, Vietnam, e Thailandia appunto. Questi macachi sono lunghi tra i 40 e i 65 centimetri, pesano dai 2,5 agli 8 chili e si cibano perlopiù di frutta, semi e piccoli invertebrati. Nel tempo si sono adattati alla convivenza con gli esseri umani e anche alla vita nelle città, forse troppo: tanto che, per quanto siano una specie protetta nel paese, sono stati classificati tra le  al mondo.I macachi di Lopburi non hanno paura degli esseri umani, che danno loro da mangiare specialmente durante la “festa delle scimmie” che si celebra l’ultima domenica di novembre, ma anzi spesso diventano aggressivi. Sono noti per portare via il cibo alle persone del posto e ai visitatori e per rubare loro telefoni, occhiali o cappelli, che in genere restituiscono solo in cambio di cibo. Di norma la gente se la cava con qualche graffio o piccole ferite, ma il fatto che di recente un uomo sia stato buttato giù dalla sua moto e che una donna si sia dislocata un ginocchio a causa di macachi affamati ha portato le autorità locali a voler prendere provvedimenti.Macachi mangiano frutta durante la festa delle scimmie a Lopburi, Thailandia, 27 novembre 2022 (AP Photo/ Chalida EKvitthayavechnukul, File)Athapol Charoenshunsa, direttore generale del dipartimento thailandese per i Parchi nazionali, la fauna selvatica e la conservazione delle piante, ha detto che circa 2.500 macachi verranno prelevati da Lopburi e trasportati in grosse aree recintate. Mercoledì in una conferenza stampa Athapol ha spiegato che il dipartimento collaborerà con scienziati ed esperti anche per trovare il modo di lasciarne un numero limitato in libertà in città.A suo dire l’idea di mettere i macachi in enormi gabbie «risolverà il problema molto velocemente»: «Non voglio che gli esseri umani siano costretti a far male alle scimmie, e non voglio che le scimmie siano costrette a far male agli esseri umani», ha detto, aggiungendo che il piano sarà attuato nel giro di alcune settimane. Per il momento sono state individuate alcune decine di “maschi alfa” che sono state trasferite nella vicina provincia di Saraburi oppure allo zoo di Lopburi; la maggior parte dei macachi verrà presa e portata via una volta che saranno completate le aree recintate, dove è prevista anche la costruzione di aree separate, di modo da limitare gli scontri fra gruppi rivali.Macachi mangiano frutta durante la festa delle scimmie a Lopburi Thailandia, 27 novembre 2022 (AP Photo/ Chalida EKvitthayavechnukul, File)Sui social network circolano molti video che mostrano decine di macachi di gruppi rivali  per strada, arrampicarsi sugli edifici di Lopburi o danneggiare le auto in cerca di cibo, tanto che la polizia locale ha cominciato a usare  per lanciare sassi verso gli animali (ma senza colpirli, ) per cercare di farli allontanare. Alcuni hanno attribuito il problema ai turisti e ai residenti che danno loro da mangiare, sostenendo che si siano abituati a ricevere il cibo e che questo abbia favorito il sovrappopolamento. Ma questa non sembra essere l’unica ragione.Sempre Athapol  che la popolazione di macachi sta aumentando perché il territorio a loro disposizione si sta riducendo a causa dell’espansione dei terreni agricoli e dello sviluppo immobiliare, mentre il cibo e l’acqua presenti in natura stanno diminuendo a causa dell’aumento generale delle temperature. Di conseguenza gli animali cercano cibo in qualsiasi posto e con qualsiasi metodo a loro disposizione, come ha spiegato il direttore dell’Ufficio per la tutela degli animali selvatici, Phadej Laithong: il risultato è che, nelle parole di Athapol, «il conflitto tra esseri umani e macachi si sta intensificando».Secondo le autorità nazionali le province che hanno problemi di gestione dei macachi sono 52 su 77. Alcune amministrazioni hanno minacciato multe per chi dà da mangiare agli animali nelle aree turistiche più frequentate, che però sono anche quelle dominate da gruppi di primati estremamente territoriali: cosa che di conseguenza ha reso più aggressivi i gruppi più deboli, che hanno cominciato a tormentare la gente in cerca di cibo anche in aree più periferiche. Tra il 2014 e il 2023 solo nella provincia di Lopburi inoltre sono stati sterilizzati circa 2.600 individui, ma quelli rimasti in città sono più o meno altrettanti.  ",
        "ranked": 14,
        "placed": "Abroad",
        "epoch": 1712300407.181892,
        "language": "IT",
        "source": "ilPost",
        "local_time": "2024-04-05 09:00:07"
    },
    {
        "title": "La speaker della camera bassa del parlamento sudafricano si è dimessa perché accusata di corruzione e riciclaggio di denaro",
        "date_raw": "April 04, 2024",
        "date": "2024-04-04",
        "url": "https://www.ilpost.it/mondo/",
        "news_url": "https://www.ilpost.it/2024/04/04/presidente-parlamento-sudafrica-dimessa-corruzione-riciclaggio/",
        "subtitle": "",
        "content": "Mercoledì Nosiviwe Mapisa-Nqakula, la speaker dell’Assemblea Nazionale sudafricana (la camera bassa del parlamento),  dopo essere stata accusata di corruzione e riciclaggio di denaro per alcuni episodi relativi al periodo in cui era stata ministra della Difesa, tra il 2014 e il 2021. Giovedì Mapisa-Nqakula si è costituita presso un ufficio di polizia, è stata arrestata e poi rilasciata su cauzione.Mapisa-Nqakula è una storica esponente del Congresso Nazionale Africano (ANC), il partito che governa il Sudafrica dalla fine dell’apartheid e che in passato fu guidato dall’ex presidente Nelson Mandela. Le accuse a suo carico e le conseguenti dimissioni potrebbe avere conseguenze anche sul partito, la cui popolarità è già ai minimi storici per altri scandali legati alla presunta corruzione dei suoi membri. Secondo alcuni  per la prima volta negli ultimi trent’anni l’ANC potrebbe non arrivare al 50 per cento dei voti alle prossime elezioni per il rinnovo del parlamento, che si terranno a maggio. ",
        "ranked": 10,
        "placed": "Abroad",
        "epoch": 1712300407.1849656,
        "language": "IT",
        "source": "ilPost",
        "local_time": "2024-04-05 09:00:07"
    },
    {
        "title": "L’industria dei microchip a Taiwan ha resistito al terremoto?",
        "date_raw": "April 04, 2024",
        "date": "2024-04-04",
        "url": "https://www.ilpost.it/mondo/",
        "news_url": "https://www.ilpost.it/2024/04/04/chip-taiwan-terremoto/",
        "subtitle": "Tutto il mondo dipende dai microchip prodotti a Taiwan per qualsiasi prodotto elettronico: per ora sembra che non ci sarà un'interruzione delle forniture, ma rimangono molti problemi",
        "content": "Il  che mercoledì ha colpito l’isola di Taiwan ha sollevato alcune  sulla tenuta della produzione locale di microchip, quei componenti essenziali per il funzionamento dei dispositivi elettronici. Circa la metà di tutti i microchip in circolazione (e l’80-90 per cento di quelli più sofisticati e importanti) è prodotta proprio a Taiwan, che ha un ruolo enorme nelle catene di fornitura globale di microchip e ospita le aziende più importanti del settore.Se le fabbriche del paese dovessero fermarsi e i microchip prodotti non dovessero riuscire a soddisfare le richieste, sarebbe un enorme problema per moltissimi dispositivi, dagli elettrodomestici ai computer, dalle automobili agli smartphone. I prezzi dei microchip potrebbero salire, esattamente com’era successo , quando erano diventati introvabili, con conseguenze anche sui prezzi dei prodotti finali per cui servono.Per quanto ci siano ancora  sull’andamento della situazione e siano in corso ancora sopralluoghi e controlli, in realtà nelle fabbriche di microchip le cose sembrano per il momento meno gravi del previsto. Le fabbriche più grandi si trovano in alcuni dei punti meno colpiti dal terremoto e, dopo una breve evacuazione, in molti stabilimenti la produzione sembra essere già ripartita. Secondo alcuni esperti, però, il terremoto  quanto sia fragile il mercato globale dei microchip, che dipende enormemente da un solo paese.In particolare,  le fabbriche della Taiwan Semiconductor Manufacturing Company, il più importante fornitore di microchip al mondo più noto come TSMC, che rifornisce aziende come Apple e Nvidia. Le sue sedi principali si trovano in zone distanti dall’epicentro del terremoto: mercoledì sono state evacuate, ma già nel pomeriggio il personale è rientrato e ha ripreso il lavoro. I danni ad alcune strumentazioni hanno intaccato solo marginalmente le produzioni, ma gli strumenti ritenuti più importanti per la continuità produttiva non sono stati danneggiati.Anche la UMC, la United Microelectronics Corporation, più piccola di TSMC ma comunque tra i più grandi produttori di microchip al mondo,  di aver evacuato i suoi stabilimenti ma che le operazioni sono poi tornate alla normalità, senza impatti significativi sulla produzione.Per quanto la gestione dell’emergenza sia ancora in corso, non sono stati registrati danni notevoli in nessuna fabbrica di Taiwan.Restano ancora molte incertezze, soprattutto perché i danni del terremoto nel settore potrebbero essere visibili solo in un secondo momento. E questo perché la produzione dei microchip è estremamente delicata, richiede ambienti stabili e isolati, senza contaminazioni esterne. È quindi possibile che, anche se gli edifici e le attrezzature non riportano danni significativi, alcuni materiali siano però compromessi. Per esempio i cosiddetti  di silicio, degli strati sottilissimi delle dimensioni di una pizza, richiedono una lavorazione precisa e ambienti controllati: anche solo un granello di polvere o un minimo graffio comprometterebbero il materiale, che quindi deve essere scartato, con conseguenti ritardi e perdite nella produzione.Un wafer di silicio (Sean Gallup/Getty Images)Le aziende si erano comunque attrezzate negli anni, sia per la delicatezza dei loro processi, sia perché Taiwan è una regione molto soggetta a terremoti. Il terremoto del 1999, paragonabile per entità a quello di mercoledì, aveva compromesso notevolmente le aziende tecnologiche, le cui produzioni furono messe in difficoltà. Negli anni successivi le aziende di microchip avevano dunque messo a punto protocolli antisismici molto rigidi e rafforzato gli impianti con le più sofisticate tecnologie antisismiche per proteggere la produzione e le attrezzature dai danni, e ripristinare le operazioni rapidamente.Molti analisti hanno fatto notare che la dipendenza del mondo dai microchip di Taiwan, per quanto sia problematica di per sé,  in situazioni del genere. Attualmente, quasi tre quarti degli impianti di fabbricazione di chip si trovano in Asia, in particolare a Taiwan, in Corea del Sud, in Cina e in Giappone. Di questi, Taiwan e Giappone sono entrambi considerati ad alto rischio sismico.Dopo la grave  avvenuta durante la pandemia, che provocò enormi ritardi nella produzione di moltissimi prodotti elettronici, l’Unione Europea e gli Stati Uniti hanno cercato di rafforzare la filiera di produzione dei microchip per ridurre la dipendenza dalle importazioni. Hanno dunque investito decine di miliardi di euro e dollari nello sviluppo locale del settore, che tuttavia è estremamente lento: per produrre i microchip, soprattutto quelli più sofisticati e di fascia più alta, servono anni – e in alcuni casi decenni – di investimenti, formazione del personale e costruzione di infrastrutture. Anche per questo molti paesi occidentali hanno stabilito accordi con le aziende taiwanesi come TSMC per costruire fabbriche fuori da Taiwan.Taiwan, tuttavia, è restìa a condividere le tecnologie per la produzione dei microchip più sofisticati, perché da questi dipende moltissimo la sua economia. I microchip sono anche un importante fattore di deterrenza contro l’intensificarsi delle ostilità della Cina, che è costretta a comprare i microchip più avanzati proprio da Taiwan, come del resto tutti i paesi del mondo. Taiwan è di fatto un paese che gode di una sovranità piena, ha un parlamento e un governo, ma la Cina  come un proprio territorio.",
        "ranked": 9,
        "placed": "Abroad",
        "epoch": 1712300407.198546,
        "language": "IT",
        "source": "ilPost",
        "local_time": "2024-04-05 09:00:07"
    },
    {
        "title": "La Finlandia ha prorogato la chiusura del confine di terra con la Russia fino a data da definirsi",
        "date_raw": "April 04, 2024",
        "date": "2024-04-04",
        "url": "https://www.ilpost.it/mondo/",
        "news_url": "https://www.ilpost.it/2024/04/04/finlandia-chiusura-indefinita-confine-russia-immigrazione/",
        "subtitle": "",
        "content": "Il ministero dell’Interno finlandese ha annunciato che il confine di terra che il paese condivide con la Russia  «fino a un’ulteriore comunicazione, ma non più di quanto sia necessario». La Finlandia  tutti gli otto varchi che collegano il paese con la Russia alla fine del 2023, a causa di un aumento insolito degli arrivi di richiedenti asilo: la Finlandia aveva quindi accusato la Russia di «strumentalizzare l’immigrazione» per destabilizzare il paese. Le chiusure decise nel 2023 sarebbero dovute scadere il 14 aprile, ma ora sono state prorogate.Il comunicato diffuso giovedì dal ministero prevede anche la chiusura di tre porti alle imbarcazioni usate a scopo ricreativo a partire dal 15 aprile. Il governo teme che con l’aumento delle temperature possa aumentare anche il numero delle persone che cerca di attraversare illegalmente il confine, lungo 1.340 chilometri in gran parte boscosi. Secondo il comunicato ci sarebbero «centinaia o forse migliaia di persone vicino al confine» che «potrebbero essere strumentalizzate ai danni della Finlandia».Da agosto a dicembre erano entrati in Finlandia tramite i varchi di frontiera con la Russia circa mille richiedenti asilo da paesi terzi, tra cui Kenya, Marocco, Pakistan, Somalia, Siria e Yemen. Di questi mille, però, più di 900 erano entrati soltanto a novembre, un aumento improvviso che secondo il governo finlandese sarebbe stato orchestrato dalla Russia. ",
        "ranked": 8,
        "placed": "Abroad",
        "epoch": 1712300407.2163417,
        "language": "IT",
        "source": "ilPost",
        "local_time": "2024-04-05 09:00:07"
    },
    {
        "title": "Secondo i media iraniani, almeno 27 persone sono state uccise in vari attacchi contro le sedi delle Guardie rivoluzionarie",
        "date_raw": "April 04, 2024",
        "date": "2024-04-04",
        "url": "https://www.ilpost.it/mondo/",
        "news_url": "https://www.ilpost.it/2024/04/04/iran-27-persone-uccise-attacco-guardia-rivoluzionaria/",
        "subtitle": "",
        "content": "Secondo quanto riportato dai media statali iraniani, nella notte tra mercoledì e giovedì  contro le sedi delle , la forza militare più potente del paese, in due città nella provincia del Sistan e Balucistan, una regione nel sud est dell’Iran al confine con Afghanistan e Pakistan.Negli attacchi, che secondo i media iraniani sono stati compiuti dal gruppo armato sunnita Jaish al-Adl, sono state uccise almeno 27 persone, di cui 11 membri delle Guardie rivoluzionarie e 16 del gruppo Jaish al-Adl.",
        "ranked": 5,
        "placed": "Abroad",
        "epoch": 1712300407.2322114,
        "language": "IT",
        "source": "ilPost",
        "local_time": "2024-04-05 09:00:07"
    },
    {
        "title": "In Danimarca uno stretto molto frequentato da navi commerciali è stato chiuso per un problema con un missile durante un’esercitazione",
        "date_raw": "April 04, 2024",
        "date": "2024-04-04",
        "url": "https://www.ilpost.it/mondo/",
        "news_url": "https://www.ilpost.it/2024/04/04/danimarca-stratto-bloccato-missile/",
        "subtitle": "",
        "content": "L’esercito danese  il traffico navale e aereo nei pressi dello stretto del Grande Belt, uno dei tre bracci di mare che collegano il mare del Nord con il mar Baltico, a causa del malfunzionamento di un missile durante un’esercitazione militare. Il missile si trova su una nave della marina danese, la Niels Juel, vicino al porto di Korsør. Dei tecnici stanno cercando di risolvere il problema.Il razzo ausiliario del missile, che serve a dargli la spinta iniziale, si è attivato e non si riesce a spegnere: rischia di lanciarlo senza controllo a qualche chilometro di distanza. Secondo l’esercito non ci sarebbe però il pericolo che il missile esploda, ma solo che si scontri con un aereo o una nave sulla sua traiettoria. Il ponte che attraversa lo stretto è invece considerato fuori pericolo, e il traffico stradale e ferroviario non sono stati interrotti.",
        "ranked": 6,
        "placed": "Abroad",
        "epoch": 1712300407.2370312,
        "language": "IT",
        "source": "ilPost",
        "local_time": "2024-04-05 09:00:07"
    },
    {
        "title": "Il principale imputato per l’attentato di Strasburgo del 2018 è stato condannato in primo grado a 30 anni di carcere",
        "date_raw": "April 04, 2024",
        "date": "2024-04-04",
        "url": "https://www.ilpost.it/mondo/",
        "news_url": "https://www.ilpost.it/2024/04/04/condanna-primo-grado-attentato-mercatino-di-natale-strasburgo/",
        "subtitle": "",
        "content": "Audrey Mondjehi, il principale accusato nel processo per l’attentato al mercatino di Natale di Strasburgo (Francia) del 2018 in cui furono uccise cinque persone, è stato  in primo grado a 30 anni di carcere. Mondjhei non partecipò direttamente all’attacco, ma secondo i giudici ebbe un ruolo centrale per procurare un’arma a Chérif Chekatt, l’autore dell’attentato poi ucciso dalla polizia durante la sua fuga.Secondo i giudici, Mondjehi sapeva che Chekatt stava preparando l’attacco poi rivendicato dallo Stato Islamico. Nel corso del processo, iniziato lo scorso febbraio, Mondjehi aveva negato di conoscere i piani di Chekatt legati all’attacco a Strasburgo. Due altre persone a processo con Mondjehi hanno ricevuto rispettivamente condanne a quattro e cinque anni di carcere per il loro ruolo nell’attentato, ma essendo rimaste a lungo in detenzione preventiva hanno già scontato parte della pena. Come Mondjehi, potranno ricorrere in appello contro la decisione del tribunale.Il mercatino di Natale di Strasburgo, il Christkindelsmärik, è tra i più antichi di Europa e attira ogni anno centinaia di migliaia di turisti. L’11 dicembre 2018 Chekatt  armato di coltello e revolver, ferì alcuni passanti e uccise cinque persone. Tra queste c’era anche il giornalista italiano .",
        "ranked": 4,
        "placed": "Abroad",
        "epoch": 1712300407.253753,
        "language": "IT",
        "source": "ilPost",
        "local_time": "2024-04-05 09:00:07"
    },
    {
        "title": "La cosiddetta Guardia costiera libica ha sparato contro una nave della ong Mediterranea che stava soccorrendo decine di migranti",
        "date_raw": "April 05, 2024",
        "date": "2024-04-05",
        "url": "https://www.ilpost.it/mondo/",
        "news_url": "https://www.ilpost.it/2024/04/05/mediterranea-mare-jonio-migranti-spari-guardia-costiera-libica/",
        "subtitle": "",
        "content": "Giovedì sera la ong Mediterranea Saving Humans ha detto che la nave Mare Jonio è stata attaccata dalla cosiddetta Guardia costiera libica, le milizie armate libiche finanziate e addestrate dall’Italia e dall’Unione Europea per fermare le partenze dei migranti, mentre stava soccorrendo decine di persone in acque internazionali. La ong ha fatto sapere che i miliziani libici hanno sparato colpi d’arma da fuoco in acqua e in aria, «creando il panico e provocando la caduta in acqua di diverse persone».Denny Castiglione, capomissione di Mediterranea, ha detto più tardi che la nave Mare Jonio è riuscita infine a soccorrere in tutto 58 persone migranti, ma che non sa quante altre siano ancora disperse dopo l’attacco della cosiddetta Guardia costiera libica.",
        "ranked": 3,
        "placed": "Abroad",
        "epoch": 1712300407.267563,
        "language": "IT",
        "source": "ilPost",
        "local_time": "2024-04-05 09:00:07"
    },
    {
        "title": "Il parlamento del Perù ha respinto due mozioni per destituire la presidente Dina Boluarte, indagata per corruzione",
        "date_raw": "April 05, 2024",
        "date": "2024-04-05",
        "url": "https://www.ilpost.it/mondo/",
        "news_url": "https://www.ilpost.it/2024/04/05/dina-boluarte-corruzione-parlamento-peru-respinge-mozioni/",
        "subtitle": "",
        "content": "Il parlamento del Perù  due mozioni presentate dai partiti di opposizione per destituire la presidente Dina Boluarte, in seguito all’indagine avviata nei suoi confronti .Boluarte è presidente ad interim del Perù dal dicembre del 2022, da quando aveva sostituito Pedro Castillo, un ex insegnante di sinistra di ispirazione marxista rimosso per aver tentato un colpo di Stato. Prima Boluarte era la sua vicepresidente.Il respingimento delle mozioni per la destituzione di Boluarte era scontato dato che la presidente può contare su un’ampia maggioranza nel parlamento, nonostante il suo consenso fra la popolazione sia molto basso.L’indagine in cui è coinvolta riguarda una collezione di una quindicina di orologi di lusso di provenienza ignota. La settimana scorsa la polizia peruviana la casa di Boluarte, che finora ha respinto ogni accusa. All’inizio delle indagini la presidente aveva ammesso di possedere almeno un Rolex, sostenendo però di averlo acquistato con quello che aveva guadagnato da quando aveva 18 anni.",
        "ranked": 2,
        "placed": "Abroad",
        "epoch": 1712300407.2951255,
        "language": "IT",
        "source": "ilPost",
        "local_time": "2024-04-05 09:00:07"
    },
    {
        "title": "La ong Open Arms ha sospeso le operazioni nella Striscia di Gaza, dopo l’attacco israeliano contro gli operatori della ong WCK",
        "date_raw": "April 05, 2024",
        "date": "2024-04-05",
        "url": "https://www.ilpost.it/mondo/",
        "news_url": "https://www.ilpost.it/2024/04/05/open-arms-gaza-wck/",
        "subtitle": "",
        "content": "Giovedì la ong spagnola Open Arms  la sospensione delle proprie operazioni umanitarie nella Striscia di Gaza, in risposta  di martedì che  sette operatori della ong World Central Kitchen nella città di Deir al Balah, nel centro della Striscia. Open Arms era stata la prima organizzazione a mandare con una nave aiuti umanitari a Gaza dopo l’invasione israeliana, nell’ambito del corridoio umanitario marittimo  dalla Commissione Europea.La ong ha detto che la nave usata per il trasporto dei primi aiuti è tornata al porto di Cipro, da cui era partita, e che non riprenderà la missione umanitaria a causa dell’attacco subito da World Central Kitchen. Finora la nave di Open Arms aveva portato a Gaza 200 tonnellate di cibo, fornito proprio dalla ong World Central Kitchen. «L’attacco compiuto dalle forze di difesa israeliane segna una dolorosa svolta nei nostri sforzi per alleviare la crisi umanitaria a Gaza», ha detto la ong in un comunicato spiegando la decisione. ",
        "ranked": 1,
        "placed": "Abroad",
        "epoch": 1712300407.3074932,
        "language": "IT",
        "source": "ilPost",
        "local_time": "2024-04-05 09:00:07"
    },
    {
        "title": "Lo Zimbabwe ha dichiarato lo stato di disastro nazionale per la siccità provocata da El Niño",
        "date_raw": "April 04, 2024",
        "date": "2024-04-04",
        "url": "https://www.ilpost.it/mondo/",
        "news_url": "https://www.ilpost.it/2024/04/04/zimbabwe-disastro-siccita-el-nino/",
        "subtitle": "",
        "content": "Mercoledì il governo dello Zimbabwe ha dichiarato  per la siccità provocata dal cosiddetto “”, l’insieme di fenomeni atmosferici che si verifica periodicamente nell’oceano Pacifico e influenza il clima di gran parte del pianeta, portando tra le altre cose a un aumento della temperatura media globale. Il presidente dello Zimbabwe, Emmerson Mnangagwa, ha detto che il paese avrà bisogno di 2 miliardi di dollari di aiuti (circa 1,8 miliardi di euro) per dare assistenza a circa 2,7 milioni di persone che rischiano di soffrire la fame.Lo Zimbabwe si trova nell’Africa meridionale, ha circa 16 milioni di abitanti e fino a pochi anni fa era un grande esportatore di prodotti agricoli, ma negli ultimi tempi ha dovuto fare ricorso sempre più spesso agli aiuti internazionali per far fronte a condizioni climatiche estreme, come ondate di calore e alluvioni. In una conferenza stampa, Mnangagwa ha detto che nei mesi estivi (da metà novembre a febbraio) sono state registrate quantità di «pioggia inferiori alla norma stagionale in più dell’80 per cento del territorio nazionale»: il risultato è che il raccolto di cereali di quest’anno basterà per soddisfare poco più della metà del fabbisogno nazionale. La siccità sta anche compromettendo la produzione di energia nelle centrali idroelettriche del paese.Lo Zimbabwe è il terzo paese della regione ad aver dichiarato lo stato di disastro a causa della siccità dopo Zambia e Malawi, che lo avevano fatto rispettivamente a febbraio e a marzo. I primi effetti di El Niño si sono visti  e secondo l’Organizzazione meteorologica mondiale (WMO) hanno raggiunto il loro picco a dicembre, ma continueranno a portare  nella gran parte del pianeta almeno fino al prossimo maggio. ",
        "ranked": 13,
        "placed": "Abroad",
        "epoch": 1712300407.314197,
        "language": "IT",
        "source": "ilPost",
        "local_time": "2024-04-05 09:00:07"
    },
    {
        "title": "Biden è sempre più spazientito con Israele, ma per ora soltanto a parole",
        "date_raw": "April 04, 2024",
        "date": "2024-04-04",
        "url": "https://www.ilpost.it/mondo/",
        "news_url": "https://www.ilpost.it/2024/04/04/biden-israele-armi-retorica/",
        "subtitle": "Il presidente statunitense ha detto al primo ministro israeliano Benjamin Netanyahu che il sostegno militare ed economico per la guerra sarà vincolato a come Israele tutelerà i civili e gli operatori umanitari a Gaza, senza annunciare azioni concrete",
        "content": "Dopo che lunedì l’esercito israeliano  (WCK) nella Striscia di Gaza, il presidente statunitense Joe Biden ha fatto le dichiarazioni più dure contro Israele da quando è cominciata la guerra:  di essere «arrabbiato e distrutto», e ha accusato Israele di non fare abbastanza per proteggere i civili della Striscia e gli operatori delle ong.Lo scontento nei confronti delle azioni del governo israeliano è stato ribadito giovedì pomeriggio nel corso di una telefonata con il primo ministro di Israele Benjamin Netanyahu, nella quale Biden  che il sostegno degli Stati Uniti nella guerra dipende da come Israele provvederà a proteggere i civili a Gaza e gli operatori umanitari. Il governo statunitense non ha però fornito ulteriori informazioni su cosa potrebbe cambiare nelle politiche verso Israele nel caso in cui fossero disattese le condizioni poste da Biden. Gli Stati Uniti si aspettano comunque di avere aggiornamenti da Israele in breve tempo sui quali basare le prossime decisioni.Le dichiarazioni fanno parte di un cambiamento notevole nell’atteggiamento di Biden, che da alcuni mesi ha cominciato a  il modo in cui Israele sta conducendo la guerra. Questo cambiamento, tuttavia, è al momento soltanto retorico: gli Stati Uniti continuano a inviare incondizionatamente a Israele grandi quantità di armi e di aiuti finanziari, che vengono usati nella guerra contro Hamas.Questo approccio di Biden nei confronti di Israele – sempre più duro e spazientito a parole, ma di sostegno completo nei fatti – sta diventando sempre più contraddittorio, e gli sta creando seri problemi politici. «Spero che questo sarà il momento in cui il presidente cambierà politica»,  al  il senatore Democratico Chris Van Hollen, riferendosi all’uccisione dei sette operatori umanitari. «Netanyahu ignora le richieste del presidente, ma noi continuiamo a inviare [a Israele] bombe da 900 chili senza restrizioni sul loro utilizzo».Varie inchieste giornalistiche  come Israele abbia lanciato bombe da 900 chili, probabilmente di produzione americana, in zone densamente popolate da civili nella Striscia di Gaza.Ci sono varie misure che Biden potrebbe adottare per ridurre la completa discrezionalità con cui Israele utilizza le armi americane e per cercare di convincere l’esercito israeliano a non colpire i civili palestinesi. La misura più forte sarebbe ovviamente ridurre o interrompere del tutto gli aiuti militari o economici. Per la situazione della politica americana oggi, in cui l’opinione pubblica è fortemente filoisraeliana, questa opzione è praticamente impensabile, ma in passato , che bloccarono gli aiuti militari o economici per convincere Israele a fermare operazioni militari troppo distruttive.Un’opzione più moderata, che molti alleati di Biden stanno chiedendo di applicare, è quella di imporre delle condizioni. Normalmente tutte le volte che gli Stati Uniti vendono o forniscono armi a un paese straniero impongono delle condizioni sul loro utilizzo. L’Ucraina, per esempio, non può usare le armi americane per attacchi contro il territorio russo, pena l’interruzione dei rifornimenti (è per questo che per colpire il territorio russo l’Ucraina utilizza armi di fabbricazione propria).Israele, tuttavia, è un’eccezione: gli Stati Uniti non impongono nessun tipo di condizione sulle armi che inviano, e questo ha fatto sì che, agli occhi di molti, Israele si sia approfittato della fiducia e abbia usato indiscriminatamente le armi nella sua guerra a Gaza, senza riguardo per i civili.Per questo la parte più di sinistra del Partito Democratico è spazientita con il presidente, che è percepito come troppo accomodante nei confronti del governo israeliano, mentre il Partito Repubblicano, che invece è solidamente filoisraeliano, sta approfittando dei tentennamenti di Biden per presentarsi come l’unico vero sostenitore di Israele: quando a fine marzo gli Stati Uniti  al Consiglio di sicurezza dell’ONU consentendo l’approvazione di una risoluzione che chiedeva un cessate il fuoco immediato, i Repubblicani hanno accusato Biden di aver abbandonato Israele e di negare il suo diritto a difendersi.Questa contraddizione sta anche mettendo in difficoltà Biden all’estero, e soprattutto nei suoi rapporti con il governo israeliano. Secondo vari esperti, Netanyahu si è ormai convinto che la retorica severa di Biden sia inconcludente. Jeremy Konyndyk, il presidente della ong Refugees International e un ex funzionario del governo di Barack Obama,  al  che il comportamento di Biden sta convincendo Netanyahu che non ci saranno conseguenze per Israele: «Quello che stiamo dicendo a Israele è: questa è soltanto retorica. […] È così che la sta trattando Netanyahu. La sta trattando come qualcosa che può ignorare senza alcuna preoccupazione».Alcuni media americani  se l’uccisione dei sette operatori di WCK potrà cambiare la posizione di Biden e renderla più dura nei confronti di Israele anche nei fatti, e non solo nella retorica. Biden tra l’altro conosce personalmente lo chef José Andrés, il capo della ong WCK che in questi giorni è stato durissimo nei confronti di Israele e degli Stati Uniti.Al momento, però, non ci sono indicazioni che lo facciano pensare. John Kirby, il portavoce della Casa Bianca, ha detto mercoledì che la posizione degli Stati Uniti nei confronti di Israele non cambia: «Siamo molto chiari sul fatto che abbiamo delle perplessità sul modo in cui sono fatte le cose [da Israele nella guerra], ma siamo molto chiari anche sul fatto che Israele continua ad avere il sostegno americano nella battaglia per eliminare la minaccia di Hamas».",
        "ranked": 15,
        "placed": "Abroad",
        "epoch": 1712300407.3252404,
        "language": "IT",
        "source": "ilPost",
        "local_time": "2024-04-05 09:00:07"
    },
    {
        "title": "La nave di World Central Kitchen che doveva consegnare 400 tonnellate di cibo nella Striscia di Gaza è tornata a Cipro",
        "date_raw": "April 03, 2024",
        "date": "2024-04-03",
        "url": "https://www.ilpost.it/mondo/",
        "news_url": "https://www.ilpost.it/2024/04/03/nave-world-central-kitchen-cipro/",
        "subtitle": "",
        "content": "Mercoledì la Jennifer, la nave cargo dell’organizzazione non governativa World Central Kitchen (WCK) che doveva consegnare 400 tonnellate di cibo alla Striscia di Gaza, è tornata, quasi piena, a Cipro. La nave era partita dal porto cipriota di Larnaca il 30 marzo e aveva raggiunto la Striscia l’1 aprile: avrebbe dovuto aspettare che il cibo venisse gradualmente scaricato e distribuito dagli operatori dell’ong prima di andarsene, ma ha interrotto tutte le operazioni dopo l’uccisione di sette di loro il 2 aprile. WCK è l’organizzazione che negli ultimi sei mesi ha distribuito più aiuti umanitari nella Striscia dopo le Nazioni Unite.Secondo , i sette operatori sono stati uccisi dall’esercito israeliano nella città di Deir al Balah, nel centro della Striscia di Gaza: il convoglio stava lasciando la città dopo aver scaricato più di 100 tonnellate di aiuti alimentari in un magazzino della zona. Il primo ministro israeliano Benjamin Netanyahu ha confermato che l’attacco è stato compiuto dal proprio esercito ma ha detto che non è successo «intenzionalmente».Secondo fonti anonime nell’esercito israeliano sentite dal quotidiano , l’attacco avrebbe avuto come obiettivo un miliziano di Hamas che sarebbe stato a bordo di un camion nel convoglio di cui facevano parte anche tre auto su cui si trovavano i sette operatori uccisi. L’attacco sarebbe stato compiuto dopo che il camion si era allontanato dal convoglio: il presunto miliziano di Hamas non sarebbe stato su nessuna delle tre auto quando sono state colpite, una dopo l’altra, da tre missili lanciati da un drone israeliano, secondo quanto riferito ad .WCK ha sede negli Stati Uniti, si occupa principalmente di fornire assistenza alimentare in posti colpiti da disastri naturali, ed è stata fondata dal noto cuoco ispano-statunitense José Andrés. Tra le altre cose ha fornito il cibo consegnato  del  di aiuti umanitari per la Striscia di Gaza. Il giornalista di  Ashraf Khalil  che l’interruzione del loro lavoro andrà quasi certamente ad aggravare quella che vari esperti definiscono «una carestia imminente», dato che «è stato interrotto un flusso di aiuti che era cruciale, disperatamente necessario in una zona sotto assedio militare». ",
        "ranked": 19,
        "placed": "Abroad",
        "epoch": 1712300407.327159,
        "language": "IT",
        "source": "ilPost",
        "local_time": "2024-04-05 09:00:07"
    },
    {
        "title": "Un gruppo di politici che si oppongono alla giunta militare che governa il Myanmar dice di aver attaccato la capitale con dei droni",
        "date_raw": "April 04, 2024",
        "date": "2024-04-04",
        "url": "https://www.ilpost.it/mondo/",
        "news_url": "https://www.ilpost.it/2024/04/04/attacco-droni-capitale-myanmar/",
        "subtitle": "",
        "content": "Il “governo di unità nazionale” (NUG) del Myanmar – cioè un gruppo di deputati e politici birmani contrari alla dittatura militare che governa il paese a seguito del  –  di aver attaccato con 29 droni equipaggiati artigianalmente con dell’esplosivo alcune infrastrutture militari a Naypyidaw, la capitale del paese.La giunta militare al potere per ora non ha commentato ufficialmente gli attacchi, e non è chiaro se questi abbiano causato morti, feriti o danni materiali. Due siti di informazione considerati vicini alla giunta hanno detto però che i droni sono stati abbattuti e che non ci sono stati morti. Al momento non è possibile verificare in modo indipendente le informazioni.I membri del NUG oggi si trovano principalmente negli Stati Uniti, ma coordinano a distanza le attività delle Forze di difesa del popolo (PDF), che sono nate nel 2021 dopo la violenta repressione di alcune proteste contro la giunta. L’attacco di giovedì sarebbe stato compiuto dalle PDF su ordine del NUG.Se fosse confermato, sarebbe un segnale della progressiva erosione del controllo della giunta militare sul paese, in cui dalla fine del 2023 si sono intensificati gli attacchi dei gruppi ribelli. Negli ultimi decenni il Myanmar è stato quasi sempre governato da dittature militari, controllate dalle potenti forze armate del paese, chiamate Tatmadaw. La giunta attuale governa dal 2021, quando un  mise fine a un periodo di aperture democratiche iniziato alcuni anni prima. La capitale Naypyidaw è stata costruita circa vent’anni fa dalla giunta precedente in una zona poco accessibile nel centro del paese, e vi si trovano numerose basi militari. ",
        "ranked": 7,
        "placed": "Abroad",
        "epoch": 1712300407.4069333,
        "language": "IT",
        "source": "ilPost",
        "local_time": "2024-04-05 09:00:07"
    }
]
