[
    {
        "title": "Autonomia, Calderoli: 'Alcune funzioni alle Regioni entro il 2025'",
        "date_raw": "Sat, 22 Feb 2025 16:28:48 +0100",
        "date": "2025-02-22",
        "url": "https://www.ansa.it/sito/notizie/politica/politica_rss.xml",
        "news_url": "https://www.ansa.it/sito/notizie/politica/2025/02/22/autonomia-calderoli-alcune-funzioni-alle-regioni-entro-il-2025_8f6f9a01-798d-4d7b-8e5e-9bf5ff86ac02.html",
        "subtitle": "'Poi si può anche affrontare il tema della sanità' ",
        "content": "Per quanto riguarda l'autonomia, \"ho dei paletti, devo rispettarli, ma penso che alcune materie possano essere trasferite alle Regioni entro la fine dell'anno\" e poi si può anche \"affrontare il tema della sanità che è il diritto civile e sociale principale che è alla base della nostra vita\". Così, nella Bergamasca. Sull'autonomia \"io non mi sono mai fermato - ha spiegato Calderoli -. Nel momento in cui la Corte costituzionale ha dichiarato che la legge è costituzionalmente legittima, magari ridimensionata, è il riconoscimento che quell'autonomia che qualcuno, anche dalle mie parti, voleva far passare per un brodino caldo, non lo era\".    \n\nRiproduzione riservata © Copyright ANSA\n\n\n\n",
        "ranked": 1,
        "placed": "Politica",
        "epoch": 1740240018.1569552,
        "language": "IT",
        "source": "ANSA",
        "local_time": "2025-02-22 17:00:18",
        "timezone": "Europe/Rome",
        "scraping_time": "2025-02-22T16.00.18",
        "en_title": "Autonomy, Calderoli: 'Some functions to the Regions by 2025'",
        "en_content": "With regard to autonomy, \"I have stakes, I must respect them, but I think that some subjects can be transferred to the regions by the end of the year\" and then you can also \"face the theme of health which is the main civil and social law that is the basis of our lives\". So, in Bergamasca. On autonomy \"I never stopped - Calderoli explained -. At the time when the Constitutional Court declared that the law is constitutionally legitimate, perhaps reorganized, it is the recognition that that autonomy that someone, even from my side, wanted to pass through a warm broth, was not\".\n\nReproduction reserved © Copyright ANSA\n\n\n\n",
        "en_subtitle": "'Then you can also address the theme of health'",
        "title_NER": [
            {
                "word": "Calderoli",
                "start_char": 10,
                "end_char": 19,
                "label": "PERSON",
                "info": "People, including fictional"
            },
            {
                "word": "2025",
                "start_char": 55,
                "end_char": 59,
                "label": "DATE",
                "info": "Absolute or relative dates or periods"
            }
        ],
        "content_NER": [
            {
                "word": "the end of the year",
                "start_char": 130,
                "end_char": 149,
                "label": "DATE",
                "info": "Absolute or relative dates or periods"
            },
            {
                "word": "Bergamasca",
                "start_char": 278,
                "end_char": 288,
                "label": "ORG",
                "info": "Companies, agencies, institutions, etc."
            },
            {
                "word": "the Constitutional Court",
                "start_char": 361,
                "end_char": 385,
                "label": "ORG",
                "info": "Companies, agencies, institutions, etc."
            }
        ]
    },
    {
        "title": "Alfieri, 'il Papa non è fuori pericolo'",
        "date_raw": "Fri, 21 Feb 2025 17:48:31 +0100",
        "date": "2025-02-21",
        "url": "https://www.ansa.it/sito/notizie/politica/politica_rss.xml",
        "news_url": "https://www.ansa.it/sito/notizie/politica/2025/02/21/alfieri-il-papa-non-e-fuori-pericolo_e6f984a9-78b5-484b-84f8-8c1b8b67b5a4.html",
        "subtitle": "Briefing al Gemelli, 'ma adesso la vita non è a rischio'",
        "content": "\n                                                \n            \"Il Papa non è fuori pericolo\". Lo ha\ndetto il professor Sergio Alfieri in un briefing al Gemelli\nsulla salute del Papa. Ma \"adesso non è in pericolo di vita,\noggi è andato in cappella a pregare\", ha aggiunto. \n                                    \n                                       \n\t\t\t\t          \n                                \n\nRiproduzione riservata © Copyright ANSA\n\n\n\n",
        "ranked": 15,
        "placed": "Politica",
        "epoch": 1740240018.1654363,
        "language": "IT",
        "source": "ANSA",
        "local_time": "2025-02-22 17:00:18",
        "timezone": "Europe/Rome",
        "scraping_time": "2025-02-22T16.00.18",
        "en_title": "Alfieri, 'the Pope is not out of danger'",
        "en_content": "\"The Pope is not out of danger.\" He did.\nsaid Professor Sergio Alfieri in a briefing at the Gemini\non the health of the Pope. But \"now is not in danger of life,\ntoday went to the chapel to pray,\" he added.\n\n\n\n\n\nReproduction reserved © Copyright ANSA\n\n\n\n",
        "en_subtitle": "Briefing at the Gemini, 'but now life is not at risk'",
        "title_NER": [
            {
                "word": "Alfieri",
                "start_char": 0,
                "end_char": 7,
                "label": "PERSON",
                "info": "People, including fictional"
            }
        ],
        "subtitle_NER": [
            {
                "word": "Gemini",
                "start_char": 16,
                "end_char": 22,
                "label": "ORG",
                "info": "Companies, agencies, institutions, etc."
            }
        ],
        "content_NER": [
            {
                "word": "Sergio Alfieri",
                "start_char": 56,
                "end_char": 70,
                "label": "PERSON",
                "info": "People, including fictional"
            },
            {
                "word": "Gemini",
                "start_char": 92,
                "end_char": 98,
                "label": "ORG",
                "info": "Companies, agencies, institutions, etc."
            },
            {
                "word": "today",
                "start_char": 161,
                "end_char": 166,
                "label": "DATE",
                "info": "Absolute or relative dates or periods"
            }
        ]
    },
    {
        "title": "Gasparri,se prosegue l'ostruzionismo al ddl sicurezza faremo dl",
        "date_raw": "Fri, 21 Feb 2025 18:34:29 +0100",
        "date": "2025-02-21",
        "url": "https://www.ansa.it/sito/notizie/politica/politica_rss.xml",
        "news_url": "https://www.ansa.it/sito/notizie/politica/2025/02/21/gasparrise-prosegue-lostruzionismo-al-ddl-sicurezza-faremo-dl_00082e61-3d79-444f-8a1d-a365e2067b04.html",
        "subtitle": "Le norme dovrebbero essere approvate all'unanimità",
        "content": "\n                                                \n            \"C'è un disegno di legge importante\nsulla sicurezza che contrasta i blocchi stradali, che rende più\nsicuro il Paese e che introduce la tutela legale. Molti\npoliziotti, carabinieri, vengono denunciati pretestuosamente e\nspendono molti soldi. Quando sono perseguitati ingiustamente è\ngiusto che la tutela legale sia finanziata dallo Stato. Il\ndisegno di legge è in discussione da molti mesi, approvato già\nalla Camera, ma in Senato c'è l'ostruzionismo del Pd e dei\ngrillini. È assurdo perché le norme per la sicurezza dovrebbero\nessere approvate all'unanimità. E se continua l'ostruzionismo,\nnoi accelereremo con un decreto-legge\". Lo dichiara il\npresidente dei senatori di Forza Italia, Maurizio Gasparri, al\nTgr Veneto. \n                                    \n                                       \n\t\t\t\t          \n                                \n\nRiproduzione riservata © Copyright ANSA\n\n\n\n",
        "ranked": 10,
        "placed": "Politica",
        "epoch": 1740240018.1795528,
        "language": "IT",
        "source": "ANSA",
        "local_time": "2025-02-22 17:00:18",
        "timezone": "Europe/Rome",
        "scraping_time": "2025-02-22T16.00.18",
        "en_title": "Gasparri, if the obstructionism continues to ddl security we will do dl",
        "en_content": "\"There is an important bill\non safety that contrasts road blocks, which makes more\nsecure the country and introducing legal protection. Many\npolice officers, carabinieri, are allegedly denounced and\nThey spend a lot of money. When they are unjustly persecuted is\njust that legal protection is funded by the state. The\nbill has been under discussion for many months, approved already\nin the Chamber, but in the Senate there is the destruction of the PD and the\nCrickets. It is absurd because safety standards should\nto be unanimously approved. And if obstructionism continues,\nwe will accelerate with a decree-law.\" It declares\npresident of the senators of Forza Italia, Maurizio Gasparri, al\nTgr Veneto.\n\n\n\n\n\nReproduction reserved © Copyright ANSA\n\n\n\n",
        "en_subtitle": "The rules should be adopted unanimously.",
        "title_NER": [
            {
                "word": "Gasparri",
                "start_char": 0,
                "end_char": 8,
                "label": "PERSON",
                "info": "People, including fictional"
            }
        ],
        "content_NER": [
            {
                "word": "many months",
                "start_char": 353,
                "end_char": 364,
                "label": "DATE",
                "info": "Absolute or relative dates or periods"
            },
            {
                "word": "Chamber",
                "start_char": 390,
                "end_char": 397,
                "label": "ORG",
                "info": "Companies, agencies, institutions, etc."
            },
            {
                "word": "Senate",
                "start_char": 410,
                "end_char": 416,
                "label": "ORG",
                "info": "Companies, agencies, institutions, etc."
            },
            {
                "word": "PD",
                "start_char": 449,
                "end_char": 451,
                "label": "GPE",
                "info": "Countries, cities, states"
            },
            {
                "word": "Forza Italia",
                "start_char": 656,
                "end_char": 668,
                "label": "ORG",
                "info": "Companies, agencies, institutions, etc."
            },
            {
                "word": "Maurizio Gasparri",
                "start_char": 670,
                "end_char": 687,
                "label": "PERSON",
                "info": "People, including fictional"
            },
            {
                "word": "al\nTgr",
                "start_char": 689,
                "end_char": 695,
                "label": "PERSON",
                "info": "People, including fictional"
            }
        ]
    },
    {
        "title": "Mons. Forte, 'non vedo necessità di parlare di dimissioni'",
        "date_raw": "Fri, 21 Feb 2025 18:41:08 +0100",
        "date": "2025-02-21",
        "url": "https://www.ansa.it/sito/notizie/politica/politica_rss.xml",
        "news_url": "https://www.ansa.it/sito/notizie/politica/2025/02/21/mons.-forte-non-vedo-necessita-di-parlare-di-dimissioni_edeab2c6-8d50-4333-aa21-ec018ca65d88.html",
        "subtitle": "\"La malattia non ha assolutamente invalidato Papa Francesco!",
        "content": "\n                                                \n            Non c'è nessuna\n\"necessità\" di parlare di dimissioni del Papa. Lo dice all'ANSA\nmonsignor Bruno Forte, arcivescovo di Chieti-Vasto, teologo\nmolto stimato da Papa Francesco che lo volle anche come\nsegretario speciale del Sinodo sulla famiglia. Nelle ultime ore\nsono diversi i cardinali che hanno parlato apertamente di questa\npossibilità.\n                                    \n                                       \n\t\t\t\t   \"Ogni ministero nella Chiesa è accettato e vissuto nella\nlibertà e le dimissioni di Papa Benedetto ne sono un esempio. Ma\nPapa Francesco ha sempre ha detto di volere andare avanti nel\nsuo ministero finché Dio gli darà la forza\", ricorda mons.\n                                    \n                                       \n\t\t\t\tForte. \"Siccome questa malattia non lo ha assolutamente\ninvalidato e sta addirittura migliorando, io non vedo la\nnecessità di parlare di dimissioni. Auguro al Papa di continuare\nil suo servizio alla Chiesa e al mondo, con la fede e con\nl'entusiasmo che ha sempre avuto\". \"Può fare ancora tanto e\ncredo che la preghiera e la Chiesa lo dovrebbe sostenere in\nquesto\", conclude. \n                                    \n                                       \n\t\t\t\t          \n                                \n\nRiproduzione riservata © Copyright ANSA\n\n\n\n",
        "ranked": 9,
        "placed": "Politica",
        "epoch": 1740240018.2005577,
        "language": "IT",
        "source": "ANSA",
        "local_time": "2025-02-22 17:00:18",
        "timezone": "Europe/Rome",
        "scraping_time": "2025-02-22T16.00.18",
        "en_title": "Mons. Strong, 'I don't see need to talk about resignation'",
        "en_content": "There's no one\n\"necessity\" to speak of resignation of the Pope. Tells the NSAID\nMonsignor Bruno Forte, archbishop of Chieti-Vasto, theologian\nmuch estimated by Pope Francis who also wanted it as\nSpecial Secretary of the Synod on the Family. In the last hours\nare different cardinals who have spoken openly of this\npossibility.\n\n\n\"Every ministry in the Church is accepted and lived in\nfreedom and resignation of Pope Benedict is an example of it. Ma\nPope Francis always said he wanted to move forward in\nHis ministry until God gives him strength,\" he recalls.\n\n\nCool. \"Like this disease has absolutely no\ndisabled and is even improving, I do not see\nneed to talk about resignation. I wish the Pope to continue\nhis service to the Church and to the world, with faith and with\nthe enthusiasm he always had.\" \"It can do so much and\nI believe that prayer and the Church should support it in\nthis,\" he concludes.\n\n\n\n\n\nReproduction reserved © Copyright ANSA\n\n\n\n",
        "en_subtitle": "\"The disease has absolutely not invalidated Pope Francis!",
        "subtitle_NER": [
            {
                "word": "Francis",
                "start_char": 49,
                "end_char": 56,
                "label": "PERSON",
                "info": "People, including fictional"
            }
        ],
        "content_NER": [
            {
                "word": "NSAID",
                "start_char": 74,
                "end_char": 79,
                "label": "ORG",
                "info": "Companies, agencies, institutions, etc."
            },
            {
                "word": "Bruno Forte",
                "start_char": 90,
                "end_char": 101,
                "label": "PERSON",
                "info": "People, including fictional"
            },
            {
                "word": "Chieti-Vasto",
                "start_char": 117,
                "end_char": 129,
                "label": "ORG",
                "info": "Companies, agencies, institutions, etc."
            },
            {
                "word": "Francis",
                "start_char": 165,
                "end_char": 172,
                "label": "PERSON",
                "info": "People, including fictional"
            },
            {
                "word": "the last hours",
                "start_char": 244,
                "end_char": 258,
                "label": "TIME",
                "info": "Times smaller than a day"
            },
            {
                "word": "Church",
                "start_char": 352,
                "end_char": 358,
                "label": "ORG",
                "info": "Companies, agencies, institutions, etc."
            },
            {
                "word": "Benedict",
                "start_char": 416,
                "end_char": 424,
                "label": "PERSON",
                "info": "People, including fictional"
            },
            {
                "word": "Francis",
                "start_char": 454,
                "end_char": 461,
                "label": "PERSON",
                "info": "People, including fictional"
            },
            {
                "word": "Church",
                "start_char": 728,
                "end_char": 734,
                "label": "ORG",
                "info": "Companies, agencies, institutions, etc."
            },
            {
                "word": "Church",
                "start_char": 857,
                "end_char": 863,
                "label": "ORG",
                "info": "Companies, agencies, institutions, etc."
            }
        ]
    },
    {
        "title": "Schlein, Meloni vassalla di Trump, si dissoci dal Cpac",
        "date_raw": "Fri, 21 Feb 2025 18:14:16 +0100",
        "date": "2025-02-21",
        "url": "https://www.ansa.it/sito/notizie/politica/politica_rss.xml",
        "news_url": "https://www.ansa.it/sito/notizie/politica/2025/02/21/schlein-meloni-vassalla-di-trump-si-dissoci-dal-cpac_4022cb6a-71fb-4888-8fcc-b10ea25b8fb8.html",
        "subtitle": "Persino Bardella ha annullato. Faccia gli interessi dell'Italia",
        "content": "\n                                                \n            \"La Presidente del Consiglio Giorgia\nMeloni da giorni non dice una parola sugli insulti e gli\nattacchi frontali di Trump all'Ucraina e all'Unione europea, non\nha il coraggio di prendere una posizione, non riesce a difendere\ngli interessi italiani ed europei perché non vuole scontentare\nla nuova amministrazione americana\". Lo dichiara la segretaria\nPd Elly Schlein. \"Addirittura apprendiamo dalla stampa che la\nPresidente Meloni sta valutando di non partecipare alla riunione\ndel G7 di lunedì e sta invece pensando di andare alla conferenza\ntrumpiana Cpac, dove Steve Bannon ha concluso il suo intervento\ncon il saluto nazista, come aveva fatto già Musk qualche\nsettimana fa. Persino Bardella ha annullato la sua\npartecipazione. Dopo questo fatto, ci chiediamo dove voglia\nportare l'Italia Giorgia Meloni, nella sua incapacità di\nscegliere tra la maglietta dell'Italia e il cappellino di Trump.\n                                    \n                                       \n\t\t\t\tAltro che ponte con gli Usa, si sta dimostrando già una\nvassalla. Abbia la decenza di dissociarsi da questo raduno\nneofascista per fare, una volta tanto, gli interessi\ndell'Italia\". \n                                    \n                                       \n\t\t\t\t          \n                                \n\nRiproduzione riservata © Copyright ANSA\n\n\n\n",
        "ranked": 12,
        "placed": "Politica",
        "epoch": 1740240018.2123199,
        "language": "IT",
        "source": "ANSA",
        "local_time": "2025-02-22 17:00:18",
        "timezone": "Europe/Rome",
        "scraping_time": "2025-02-22T16.00.18",
        "en_title": "Schlein, Trump's Meloni Vassalla, dissociated from Cpac",
        "en_content": "\"The President of the Giorgia Council\nMeloni hasn't spoken a word about insults and insults for days\nTrump's frontal attacks on Ukraine and the European Union, not\nhas the courage to take a position, can not defend\nthe Italian and European interests because it does not want to displease\nthe new American administration\". The secretary declares it\nPd Elly Schlein. \"Addirittura learns from the press that the\nPresident Meloni is considering not to attend the meeting\nof the G7 of Monday and is instead thinking of going to the conference\ntrumpiana Cpac, where Steve Bannon concluded his intervention\nwith the Nazi greeting, as Musk had already done some\nweek ago. Even Bardella canceled his\nparticipation. After this, we wonder where you want\nbring Italy Giorgia Meloni, in his inability to\nchoose between the shirt of Italy and Trump's cap.\n\n\nOther than bridge with the U.S., it is already showing a\nVassalla. Have the decency to dissociate from this gathering\nneo-fascist to do, once in a while, the interests\nof Italy\".\n\n\n\n\n\nReproduction reserved © Copyright ANSA\n\n\n\n",
        "en_subtitle": "Even Bardella canceled. Make the interests of Italy",
        "title_NER": [
            {
                "word": "Schlein",
                "start_char": 0,
                "end_char": 7,
                "label": "PERSON",
                "info": "People, including fictional"
            },
            {
                "word": "Trump",
                "start_char": 9,
                "end_char": 14,
                "label": "ORG",
                "info": "Companies, agencies, institutions, etc."
            },
            {
                "word": "Meloni Vassalla",
                "start_char": 17,
                "end_char": 32,
                "label": "PERSON",
                "info": "People, including fictional"
            },
            {
                "word": "Cpac",
                "start_char": 51,
                "end_char": 55,
                "label": "GPE",
                "info": "Countries, cities, states"
            }
        ],
        "subtitle_NER": [
            {
                "word": "Bardella",
                "start_char": 5,
                "end_char": 13,
                "label": "PERSON",
                "info": "People, including fictional"
            },
            {
                "word": "Italy",
                "start_char": 46,
                "end_char": 51,
                "label": "GPE",
                "info": "Countries, cities, states"
            }
        ],
        "content_NER": [
            {
                "word": "Giorgia Council",
                "start_char": 22,
                "end_char": 37,
                "label": "ORG",
                "info": "Companies, agencies, institutions, etc."
            },
            {
                "word": "Meloni",
                "start_char": 38,
                "end_char": 44,
                "label": "PERSON",
                "info": "People, including fictional"
            },
            {
                "word": "days",
                "start_char": 96,
                "end_char": 100,
                "label": "DATE",
                "info": "Absolute or relative dates or periods"
            },
            {
                "word": "Trump",
                "start_char": 101,
                "end_char": 106,
                "label": "ORG",
                "info": "Companies, agencies, institutions, etc."
            },
            {
                "word": "Ukraine",
                "start_char": 128,
                "end_char": 135,
                "label": "GPE",
                "info": "Countries, cities, states"
            },
            {
                "word": "the European Union",
                "start_char": 140,
                "end_char": 158,
                "label": "ORG",
                "info": "Companies, agencies, institutions, etc."
            },
            {
                "word": "Italian",
                "start_char": 219,
                "end_char": 226,
                "label": "NORP",
                "info": "Nationalities or religious or political groups"
            },
            {
                "word": "European",
                "start_char": 231,
                "end_char": 239,
                "label": "NORP",
                "info": "Nationalities or religious or political groups"
            },
            {
                "word": "American",
                "start_char": 296,
                "end_char": 304,
                "label": "NORP",
                "info": "Nationalities or religious or political groups"
            },
            {
                "word": "Elly Schlein",
                "start_char": 351,
                "end_char": 363,
                "label": "PERSON",
                "info": "People, including fictional"
            },
            {
                "word": "Addirittura",
                "start_char": 366,
                "end_char": 377,
                "label": "PERSON",
                "info": "People, including fictional"
            },
            {
                "word": "Meloni",
                "start_char": 419,
                "end_char": 425,
                "label": "PERSON",
                "info": "People, including fictional"
            },
            {
                "word": "G7",
                "start_char": 474,
                "end_char": 476,
                "label": "ORG",
                "info": "Companies, agencies, institutions, etc."
            },
            {
                "word": "Monday",
                "start_char": 480,
                "end_char": 486,
                "label": "DATE",
                "info": "Absolute or relative dates or periods"
            },
            {
                "word": "Cpac",
                "start_char": 548,
                "end_char": 552,
                "label": "GPE",
                "info": "Countries, cities, states"
            },
            {
                "word": "Steve Bannon",
                "start_char": 560,
                "end_char": 572,
                "label": "PERSON",
                "info": "People, including fictional"
            },
            {
                "word": "Nazi",
                "start_char": 609,
                "end_char": 613,
                "label": "NORP",
                "info": "Nationalities or religious or political groups"
            },
            {
                "word": "Musk",
                "start_char": 627,
                "end_char": 631,
                "label": "PERSON",
                "info": "People, including fictional"
            },
            {
                "word": "some\nweek ago",
                "start_char": 649,
                "end_char": 662,
                "label": "DATE",
                "info": "Absolute or relative dates or periods"
            },
            {
                "word": "Bardella",
                "start_char": 669,
                "end_char": 677,
                "label": "PERSON",
                "info": "People, including fictional"
            },
            {
                "word": "Italy",
                "start_char": 749,
                "end_char": 754,
                "label": "GPE",
                "info": "Countries, cities, states"
            },
            {
                "word": "Giorgia Meloni",
                "start_char": 755,
                "end_char": 769,
                "label": "PERSON",
                "info": "People, including fictional"
            },
            {
                "word": "Italy",
                "start_char": 819,
                "end_char": 824,
                "label": "GPE",
                "info": "Countries, cities, states"
            },
            {
                "word": "Trump",
                "start_char": 829,
                "end_char": 834,
                "label": "ORG",
                "info": "Companies, agencies, institutions, etc."
            },
            {
                "word": "U.S.",
                "start_char": 871,
                "end_char": 875,
                "label": "GPE",
                "info": "Countries, cities, states"
            },
            {
                "word": "Vassalla",
                "start_char": 901,
                "end_char": 909,
                "label": "PERSON",
                "info": "People, including fictional"
            },
            {
                "word": "Italy",
                "start_char": 1015,
                "end_char": 1020,
                "label": "GPE",
                "info": "Countries, cities, states"
            }
        ]
    },
    {
        "title": "A.Fontana: 'Preghiera per bimbi uccisi non richiede riflessione'",
        "date_raw": "Fri, 21 Feb 2025 20:11:52 +0100",
        "date": "2025-02-21",
        "url": "https://www.ansa.it/sito/notizie/politica/politica_rss.xml",
        "news_url": "https://www.ansa.it/sito/notizie/politica/2025/02/21/a.fontana-preghiera-per-bimbi-uccisi-non-richiede-riflessione_0ad9ca7e-572a-4856-91d3-57e41e04132c.html",
        "subtitle": "Illuminati i palazzi della Regione Lombardia per Ariel e Kfir",
        "content": "\n                                                \n            \"Ho aderito senza esitazione alla\nrichiesta pervenuta mercoledì sera. Una preghiera per ostaggi\nuccisi in prigionia non richiede alcuna riflessione politica\".\n                                    \n                                       \n\t\t\t\tCosì il presidente della Regione Lombardia, Attilio Fontana,\nsulla richiesta dell'Associazione milanese Pro Israele di\nilluminare Palazzo Lombardia e Palazzo Pirelli di arancione in\nsegno di vicinanza per la restituzione della salme dei due\nbambini Ariel e Kfir da parte di Hamas. \n                                    \n                                       \n\t\t\t\t          \n                                \n\nRiproduzione riservata © Copyright ANSA\n\n\n\n",
        "ranked": 8,
        "placed": "Politica",
        "epoch": 1740240018.219168,
        "language": "IT",
        "source": "ANSA",
        "local_time": "2025-02-22 17:00:18",
        "timezone": "Europe/Rome",
        "scraping_time": "2025-02-22T16.00.18",
        "en_title": "A.Fontana: 'Prayer for children killed does not require reflection'",
        "en_content": "\"I have adhered without hesitation to\nrequest received Wednesday evening. A prayer for hostages\nkilled in captivity requires no political reflection.\"\n\n\nThus the president of the Lombardy Region, Attilio Fontana,\non the request of the Pro Israel Milanese Association\nilluminate Palazzo Lombardia and Palazzo Pirelli di orange in\nsign of closeness for the return of the body of the two\nAriel and Kfir children from Hamas.\n\n\n\n\n\nReproduction reserved © Copyright ANSA\n\n\n\n",
        "en_subtitle": "Illuminati i palazzi della Regione Lombardia per Ariel e Kfir",
        "subtitle_NER": [
            {
                "word": "Illuminati",
                "start_char": 0,
                "end_char": 10,
                "label": "NORP",
                "info": "Nationalities or religious or political groups"
            },
            {
                "word": "della Regione",
                "start_char": 21,
                "end_char": 34,
                "label": "PERSON",
                "info": "People, including fictional"
            },
            {
                "word": "Ariel e Kfir",
                "start_char": 49,
                "end_char": 61,
                "label": "ORG",
                "info": "Companies, agencies, institutions, etc."
            }
        ],
        "content_NER": [
            {
                "word": "Wednesday",
                "start_char": 55,
                "end_char": 64,
                "label": "DATE",
                "info": "Absolute or relative dates or periods"
            },
            {
                "word": "evening",
                "start_char": 65,
                "end_char": 72,
                "label": "TIME",
                "info": "Times smaller than a day"
            },
            {
                "word": "the Lombardy Region",
                "start_char": 175,
                "end_char": 194,
                "label": "GPE",
                "info": "Countries, cities, states"
            },
            {
                "word": "Attilio Fontana",
                "start_char": 196,
                "end_char": 211,
                "label": "PERSON",
                "info": "People, including fictional"
            },
            {
                "word": "the Pro Israel Milanese Association",
                "start_char": 231,
                "end_char": 266,
                "label": "ORG",
                "info": "Companies, agencies, institutions, etc."
            },
            {
                "word": "Palazzo Lombardia",
                "start_char": 278,
                "end_char": 295,
                "label": "ORG",
                "info": "Companies, agencies, institutions, etc."
            },
            {
                "word": "Palazzo Pirelli di",
                "start_char": 300,
                "end_char": 318,
                "label": "ORG",
                "info": "Companies, agencies, institutions, etc."
            },
            {
                "word": "two",
                "start_char": 381,
                "end_char": 384,
                "label": "CARDINAL",
                "info": "Numerals that do not fall under another type"
            },
            {
                "word": "Ariel",
                "start_char": 385,
                "end_char": 390,
                "label": "PERSON",
                "info": "People, including fictional"
            },
            {
                "word": "Hamas",
                "start_char": 414,
                "end_char": 419,
                "label": "ORG",
                "info": "Companies, agencies, institutions, etc."
            }
        ]
    },
    {
        "title": "Manfredi, sicurezza non è patrimonio della destra",
        "date_raw": "Sat, 22 Feb 2025 13:40:19 +0100",
        "date": "2025-02-22",
        "url": "https://www.ansa.it/sito/notizie/politica/politica_rss.xml",
        "news_url": "https://www.ansa.it/sito/notizie/politica/2025/02/22/manfredi-sicurezza-non-e-patrimonio-della-destra_b35e01a8-9a45-43b2-a3b0-c4f0f67ae31b.html",
        "subtitle": "'La gente delle periferie vota noi e la dobbiamo difendere'",
        "content": "\n                                                \n            \"La sicurezza non è patrimonio\ndella destra, ma della sinistra. Chi soffre nelle nostre\nperiferie  sono le persone che votano noi e noi li dobbiamo\ndifendere, ma lo dobbiamo fare con il nostro approccio alla\nsicurezza che significa separare il bisogno dalla criminalità: i\ncriminali vanno perseguiti mentre le persone bisognose vanno\naiutate. Noi non saremo mai maggioranza se non saremo in grado\ndi dare risposte a questi bisogni\". Lo ha affermato il\npresidente nazionale Anci e sindaco di Napoli, Gaetano Manfredi,\nnel corso del suo intervento alla prima Conferenza nazionale\ndelle elette e degli eletti di Avs nei Consigli comunali, ed ha\naggiunto: \"L'unico modo è avere cura delle persone e della\nprossimità. Se riusciremo a fare questo, partendo dai territori,\navremo un'Italia migliore ed è quello che noi vogliamo\". \n                                    \n                                       \n\t\t\t\t          \n                                \n\nRiproduzione riservata © Copyright ANSA\n\n\n\n",
        "ranked": 5,
        "placed": "Politica",
        "epoch": 1740240018.2282052,
        "language": "IT",
        "source": "ANSA",
        "local_time": "2025-02-22 17:00:18",
        "timezone": "Europe/Rome",
        "scraping_time": "2025-02-22T16.00.18",
        "en_title": "Manfredi, security is not the right heritage",
        "en_content": "\"Security is not heritage\nof the right, but of the left. Who suffers in our\nthe people who vote for us and we must\nto defend, but we must do so with our approach to\nsecurity that means separating the need from crime: I\ncriminals are being pursued while needy people go\nHelp. We will never be a majority unless we can\nto give answers to these needs.\" He said that\nNational President Anci and Mayor of Naples, Gaetano Manfredi,\nduring his speech at the first National Conference\nof the Elettes and the Elects of Avs in the City Councils, and has\nadded: \"The only way is to take care of people and the\nproximity. If we can do this, starting from the territories,\nwe will have a better Italy and that's what we want.\"\n\n\n\n\n\nReproduction reserved © Copyright ANSA\n\n\n\n",
        "en_subtitle": "'The people of the suburbs vote us and we must defend it'",
        "title_NER": [
            {
                "word": "Manfredi",
                "start_char": 0,
                "end_char": 8,
                "label": "GPE",
                "info": "Countries, cities, states"
            }
        ],
        "content_NER": [
            {
                "word": "Anci",
                "start_char": 382,
                "end_char": 386,
                "label": "PERSON",
                "info": "People, including fictional"
            },
            {
                "word": "Naples",
                "start_char": 400,
                "end_char": 406,
                "label": "GPE",
                "info": "Countries, cities, states"
            },
            {
                "word": "Gaetano Manfredi",
                "start_char": 408,
                "end_char": 424,
                "label": "PERSON",
                "info": "People, including fictional"
            },
            {
                "word": "first",
                "start_char": 451,
                "end_char": 456,
                "label": "ORDINAL",
                "info": "\"first\", \"second\", etc."
            },
            {
                "word": "Elettes",
                "start_char": 484,
                "end_char": 491,
                "label": "FAC",
                "info": "Buildings, airports, highways, bridges, etc."
            },
            {
                "word": "Avs",
                "start_char": 510,
                "end_char": 513,
                "label": "PRODUCT",
                "info": "Objects, vehicles, foods, etc. (not services)"
            },
            {
                "word": "the City Councils",
                "start_char": 517,
                "end_char": 534,
                "label": "ORG",
                "info": "Companies, agencies, institutions, etc."
            },
            {
                "word": "Italy",
                "start_char": 682,
                "end_char": 687,
                "label": "GPE",
                "info": "Countries, cities, states"
            }
        ]
    }
]
